setup.py
pun_probability/Binomialdistribution.py
pun_probability/Gaussiandistribution.py
pun_probability/Generaldistribution.py
pun_probability/__init__.py
pun_probability.egg-info/PKG-INFO
pun_probability.egg-info/SOURCES.txt
pun_probability.egg-info/dependency_links.txt
pun_probability.egg-info/not-zip-safe
pun_probability.egg-info/top_level.txt