Metadata-Version: 2.1
Name: pun-probability
Version: 0.1
Summary: Gaussian and Binomial distributions
Home-page: UNKNOWN
Author: Tawatwee Aiem
Author-email: punnyoz1103@gmail.com
License: UNKNOWN
Platform: UNKNOWN
